autonicer/__init__.py
autonicer/__main__.py
autonicer/autonicer.py
autonicer/reprocess.py
autonicer-1.3.0.dist-info/LICENSE
autonicer-1.3.0.dist-info/METADATA
autonicer-1.3.0.dist-info/WHEEL
autonicer-1.3.0.dist-info/entry_points.txt
autonicer-1.3.0.dist-info/top_level.txt
autonicer-1.3.0.dist-info/RECORD
