Metadata-Version: 2.2
Name: autonicer
Version: 1.3.0
Summary: A program that retrieves NICER observational data sets and performs a default data reduction process on the NICER observational data
Author-email: Tsar Bomba Nick <njkuechel@protonmail.com>
License:                                  Apache License
Requires-Python: >=3.8
License-File: LICENSE
Requires-Dist: astropy>=4.2.1
Requires-Dist: astroquery>=0.4.8
Requires-Dist: numpy>=1.20.3
Requires-Dist: pandas>=1.2.4
Requires-Dist: termcolor>=1.1.0
Requires-Dist: certifi>=2022.12.7
Requires-Dist: cryptography>=41.0.2
Requires-Dist: requests>=2.31.0
Requires-Dist: tqdm>=4.67.1
Requires-Dist: aiohttp>=3.11.12
Provides-Extra: dev
Requires-Dist: pytest-cov>=3.0.0; extra == "dev"
Requires-Dist: pytest>=7.2.0; extra == "dev"
Requires-Dist: build>=0.10.0; extra == "dev"
Requires-Dist: flake8>=7.1.1; extra == "dev"
